{
	"description": "项目配置文件",
	"packOptions": {
		"ignore": []
	},
	"setting": {
		"urlCheck": false,
		"es6": true,
		"postcss": true,
		"minified": true,
		"newFeature": true,
		"autoAudits": false
	},
	"compileType": "miniprogram",
	"libVersion": "2.8.1",
	"appid": "wxd29b1aef999221b0",
	"projectname": "WasteSorting",
	"debugOptions": {
		"hidedInDevtools": []
	},
	"isGameTourist": false,
	"condition": {
		"search": {
			"current": -1,
			"list": []
		},
		"conversation": {
			"current": -1,
			"list": []
		},
		"plugin": {
			"current": -1,
			"list": []
		},
		"game": {
			"currentL": -1,
			"list": []
		},
		"miniprogram": {
			"current": 3,
			"list": [
				{
					"id": -1,
					"name": "address",
					"pathName": "pages/address/index",
					"query": ""
				},
				{
					"id": 1,
					"name": "orderForm",
					"pathName": "pages/orderForm/index",
					"query": ""
				},
				{
					"id": -1,
					"name": "package",
					"pathName": "pages/package/index",
					"query": ""
				},
				{
					"id": -1,
					"name": "package",
					"pathName": "pages/my/index",
					"query": ""
				}
			]
		}
	}
}